create_shortcut.py
pomera.py
pomera_mcp_server.py
core/__init__.py
core/ai_tools_engine.py
core/app_context.py
core/async_text_processor.py
core/backup_manager.py
core/backup_recovery_manager.py
core/collapsible_panel.py
core/content_hash_cache.py
core/context_menu.py
core/data_directory.py
core/data_validator.py
core/database_connection_manager.py
core/database_curl_settings_manager.py
core/database_promera_ai_settings_manager.py
core/database_schema.py
core/database_schema_manager.py
core/database_settings_manager.py
core/database_settings_manager_interface.py
core/dialog_manager.py
core/diff_utils.py
core/efficient_line_numbers.py
core/error_handler.py
core/error_service.py
core/event_consolidator.py
core/load_presets_dialog.py
core/mcp_security_manager.py
core/memento.py
core/memory_efficient_text_widget.py
core/migration_manager.py
core/migration_test_suite.py
core/migration_validator.py
core/note_encryption.py
core/optimized_find_replace.py
core/optimized_pattern_engine.py
core/optimized_search_highlighter.py
core/performance_monitor.py
core/persistence_manager.py
core/progressive_stats_calculator.py
core/regex_pattern_cache.py
core/regex_pattern_library.py
core/search_operation_manager.py
core/semantic_diff.py
core/semantic_diff_operators.py
core/settings_defaults_registry.py
core/settings_integrity_validator.py
core/settings_serializer.py
core/settings_validator.py
core/smart_stats_calculator.py
core/statistics_update_manager.py
core/stats_config_manager.py
core/streaming_text_handler.py
core/task_scheduler.py
core/tool_search_widget.py
core/update_pattern_library.py
core/visibility_monitor.py
core/widget_cache.py
core/mcp/__init__.py
core/mcp/file_io_helpers.py
core/mcp/find_replace_diff.py
core/mcp/protocol.py
core/mcp/schema.py
core/mcp/server_stdio.py
core/mcp/tool_registry.py
pomera/__init__.py
pomera/_version.py
pomera/version.py
pomera_ai_commander-1.3.7.dist-info/licenses/LICENSE
tools/__init__.py
tools/ai_tools.py
tools/ascii_art_generator.py
tools/base64_tools.py
tools/base_tool.py
pomera_ai_commander-1.3.7.dist-info/METADATA
pomera_ai_commander-1.3.7.dist-info/WHEEL
pomera_ai_commander-1.3.7.dist-info/entry_points.txt
pomera_ai_commander-1.3.7.dist-info/top_level.txt
pomera_ai_commander-1.3.7.dist-info/RECORD
