Metadata-Version: 2.4
Name: pomera-ai-commander
Version: 1.3.7
Summary: Text processing toolkit with 22 MCP tools for AI assistants - case transformation, encoding, hashing, text analysis, and notes management
Author-email: matbanik <matbanik@users.noreply.github.com>
Maintainer-email: matbanik <matbanik@users.noreply.github.com>
License: MIT
Project-URL: Homepage, https://github.com/matbanik/Pomera-AI-Commander
Project-URL: Documentation, https://github.com/matbanik/Pomera-AI-Commander#readme
Project-URL: Repository, https://github.com/matbanik/Pomera-AI-Commander
Project-URL: Issues, https://github.com/matbanik/Pomera-AI-Commander/issues
Project-URL: Changelog, https://github.com/matbanik/Pomera-AI-Commander/releases
Keywords: mcp,model-context-protocol,text-processing,ai-tools,pomera,text-manipulation,encoding,hashing,notes,cursor,claude-desktop
Classifier: Development Status :: 4 - Beta
Classifier: Environment :: Console
Classifier: Intended Audience :: Developers
Classifier: License :: OSI Approved :: MIT License
Classifier: Operating System :: OS Independent
Classifier: Programming Language :: Python :: 3
Classifier: Programming Language :: Python :: 3.8
Classifier: Programming Language :: Python :: 3.9
Classifier: Programming Language :: Python :: 3.10
Classifier: Programming Language :: Python :: 3.11
Classifier: Programming Language :: Python :: 3.12
Classifier: Programming Language :: Python :: 3.13
Classifier: Topic :: Software Development :: Libraries :: Python Modules
Classifier: Topic :: Text Processing
Classifier: Topic :: Utilities
Requires-Python: >=3.8
License-File: LICENSE
Requires-Dist: requests>=2.25.0
Requires-Dist: platformdirs>=4.0.0
Requires-Dist: deepdiff<9.0.0,>=6.7.0
Requires-Dist: PyYAML>=6.0.0
Requires-Dist: json5>=0.9.0
Requires-Dist: jsonschema>=4.0.0
Requires-Dist: tomli>=2.0.0; python_version < "3.11"
Provides-Extra: gui
Requires-Dist: reportlab>=3.6.0; extra == "gui"
Requires-Dist: python-docx>=0.8.0; extra == "gui"
Requires-Dist: rapidfuzz>=3.0.0; extra == "gui"
Provides-Extra: full
Requires-Dist: reportlab>=3.6.0; extra == "full"
Requires-Dist: python-docx>=0.8.0; extra == "full"
Requires-Dist: rapidfuzz>=3.0.0; extra == "full"
Requires-Dist: pyaudio>=0.2.0; extra == "full"
Requires-Dist: numpy>=1.20.0; extra == "full"
Requires-Dist: psutil>=5.8.0; extra == "full"
Requires-Dist: huggingface-hub>=0.10.0; extra == "full"
Provides-Extra: dev
Requires-Dist: pytest>=7.0.0; extra == "dev"
Requires-Dist: pytest-cov>=4.0.0; extra == "dev"
Requires-Dist: black>=23.0.0; extra == "dev"
Requires-Dist: isort>=5.12.0; extra == "dev"
Requires-Dist: mypy>=1.0.0; extra == "dev"
Dynamic: license-file
